{
  "posts": [
    {
      "id": 1,
      "title": "First Question",
      "description" : "First Question Description"
    },
    {
      "id": 2,
      "title": "Second Question",
      "description" : "Second Question Description"
    },
    {
      "id": 3,
      "title": "Third Question",
      "description" : "Third Question Description"
    },
    {
      "id": 4,
      "title": "Fourth Question",
      "description" : "Fourth Question Description"
    },
    {
      "id": 5,
      "title": "Fifth Question",
      "description" : "Fifth Question Description"
    }
  ],
  "profile": {
    "name": "typicode"
  }
}
